AnalysisG-4.5.8.dist-info/WHEEL
AnalysisG-4.5.8.dist-info/LICENSE
AnalysisG-4.5.8.dist-info/top_level.txt
AnalysisG-4.5.8.dist-info/entry_points.txt
AnalysisG-4.5.8.dist-info/RECORD
AnalysisG-4.5.8.dist-info/METADATA
AnalysisG/__main__.py
AnalysisG/__init__.py
AnalysisG/Submission/__init__.py
AnalysisG/Submission/Condor.py
AnalysisG/Submission/script_builder.py
AnalysisG/_cmodules/__init__.py
AnalysisG/_cmodules/cWrapping.cpython-38-x86_64-linux-gnu.so
AnalysisG/_cmodules/code.cpython-38-x86_64-linux-gnu.so
AnalysisG/_cmodules/GraphTemplate.cpython-38-x86_64-linux-gnu.so
AnalysisG/_cmodules/SelectionTemplate.cpython-38-x86_64-linux-gnu.so
AnalysisG/_cmodules/MetaData.cpython-38-x86_64-linux-gnu.so
AnalysisG/_cmodules/SampleTracer.cpython-38-x86_64-linux-gnu.so
AnalysisG/_cmodules/EventTemplate.cpython-38-x86_64-linux-gnu.so
AnalysisG/_cmodules/ParticleTemplate.cpython-38-x86_64-linux-gnu.so
AnalysisG/_cmodules/Runner.cpython-38-x86_64-linux-gnu.so
AnalysisG/_cmodules/ctools.cpython-38-x86_64-linux-gnu.so
AnalysisG/_cmodules/cOptimizer.cpython-38-x86_64-linux-gnu.so
AnalysisG/_cmodules/cPlots.cpython-38-x86_64-linux-gnu.so
AnalysisG/_cmodules/epoch/epoch.cxx
AnalysisG/_cmodules/epoch/epoch.h
AnalysisG/_cmodules/plotting/plotting.h
AnalysisG/_cmodules/plotting/plotting.cxx
AnalysisG/_cmodules/selection/selection.cxx
AnalysisG/_cmodules/selection/selection.h
AnalysisG/_cmodules/graph/graph.cxx
AnalysisG/_cmodules/graph/graph.h
AnalysisG/_cmodules/root/root.cxx
AnalysisG/_cmodules/root/root.h
AnalysisG/_cmodules/sampletracer/sampletracer.cxx
AnalysisG/_cmodules/sampletracer/sampletracer.h
AnalysisG/_cmodules/event/event.h
AnalysisG/_cmodules/event/event.cxx
AnalysisG/_cmodules/abstractions/abstractions.h
AnalysisG/_cmodules/abstractions/cytypes.h
AnalysisG/_cmodules/abstractions/abstractions.cxx
AnalysisG/_cmodules/metadata/metadata.cxx
AnalysisG/_cmodules/metadata/metadata.h
AnalysisG/_cmodules/cyincludes/cysampletracer.cpp
AnalysisG/_cmodules/cyincludes/cywrapping.pxd
AnalysisG/_cmodules/cyincludes/cymetadata.pyx
AnalysisG/_cmodules/cyincludes/cysampletracer.pyx
AnalysisG/_cmodules/cyincludes/cywrapping.pyx
