Metadata-Version: 2.1
Name: AnalysisG
Version: 4.5.8
Author: woywoy123
Project-URL: Homepage, https://github.com/woywoy123/AnalysisG
Classifier: License :: OSI Approved :: MIT License
Classifier: Programming Language :: Python :: 3.7
Classifier: Programming Language :: Python :: 3.8
Classifier: Programming Language :: Python :: 3.9
Classifier: Programming Language :: Python :: 3.10
Classifier: Programming Language :: Python :: 3.11
Classifier: Programming Language :: Python :: 3.12
Classifier: Programming Language :: Cython
Classifier: Programming Language :: C++
Requires-Python: >=3.7
License-File: LICENSE
Requires-Dist: mplhep==0.3.28
Requires-Dist: matplotlib==3.5.3
Requires-Dist: pyAMI-atlas==5.1.0.1
Requires-Dist: awkward<=2.4.4
Requires-Dist: uproot
Requires-Dist: numpy
Requires-Dist: h5py
Requires-Dist: pwinput
Requires-Dist: scikit-learn
Requires-Dist: torchmetrics
Requires-Dist: torch-geometric
Requires-Dist: boost_histogram
